pyhkc/__init__.py
pyhkc/hkc_api.py
pyhkc-0.5.0.dist-info/licenses/LICENSE
pyhkc-0.5.0.dist-info/METADATA
pyhkc-0.5.0.dist-info/WHEEL
pyhkc-0.5.0.dist-info/top_level.txt
pyhkc-0.5.0.dist-info/RECORD
