Metadata-Version: 2.4
Name: pyhkc
Version: 0.5.0
Summary: A Python client for HKC SecureComm API
Home-page: https://github.com/jasonmadigan/pyhkc
Author: Jason Madigan
Author-email: jason@jasonmadigan.com
Classifier: Programming Language :: Python :: 3
Classifier: License :: OSI Approved :: Apache Software License
Classifier: Operating System :: OS Independent
License-File: LICENSE
Requires-Dist: requests
Requires-Dist: tabulate==0.9.0
Requires-Dist: tenacity==8.3.0
Dynamic: author
Dynamic: author-email
Dynamic: classifier
Dynamic: description
Dynamic: description-content-type
Dynamic: home-page
Dynamic: license-file
Dynamic: requires-dist
Dynamic: summary
